{
    "visual basic": "", 
    "4th dimension": "", 
    "abap": "", 
    "abc": "", 
    "actionscript": "", 
    "ada": "", 
    "agilent vee": "", 
    "algol": "", 
    "alice": "", 
    "angelscript": "", 
    "apex": "", 
    "apl": "", 
    "applescript": "", 
    "arc": "", 
    "arduino": "", 
    "asp": "", 
    "aspectj": "", 
    "assembly": "", 
    "atlas": "", 
    "augeas": "", 
    "autohotkey": "", 
    "autoit": "", 
    "autolisp": "", 
    "automator": "", 
    "avenue": "", 
    "awk": "", 
    "bash": "", 
    "bc": "", 
    "bcpl": "", 
    "beta": "", 
    "blitzmax": "", 
    "boo": "", 
    "bourne shell": "", 
    "bro": "", 
    "c": "", 
    "c shell": "", 
    "c#": "", 
    "c++": "", 
    "c-omega": "", 
    "caml": "", 
    "ceylon": "", 
    "cfml": "", 
    "cg": "", 
    "ch": "", 
    "chill": "", 
    "cil": "", 
    "clarion": "", 
    "clean": "", 
    "clipper": "", 
    "clojure": "", 
    "clu": "", 
    "cobol": "", 
    "cobra": "", 
    "coffeescript": "", 
    "coldfusion": "", 
    "comal": "", 
    "common lisp": "", 
    "coq": "", 
    "ct": "", 
    "curl": "", 
    "d": "", 
    "dart": "", 
    "dcl": "", 
    "dcpu-16 asm": "", 
    "delphi": "", 
    "dibol": "", 
    "dylan": "", 
    "e": "", 
    "ec": "", 
    "ecl": "", 
    "ecmascript": "", 
    "egl": "", 
    "eiffel": "", 
    "elixir": "", 
    "emacs lisp": "", 
    "erlang": "", 
    "etoys": "", 
    "euphoria": "", 
    "exec": "", 
    "f#": "", 
    "factor": "", 
    "falcon": "", 
    "fancy": "", 
    "fantom": "", 
    "felix": "", 
    "forth": "", 
    "fortran": "", 
    "fortress": "", 
    "foxpro": "", 
    "gambas": "", 
    "genie": "", 
    "gnu octave": "", 
    "go": "", 
    "google appsscript": "", 
    "gosu": "", 
    "groovy": "", 
    "haskell": "", 
    "haxe": "", 
    "heron": "", 
    "hpl": "", 
    "html": "", 
    "hypertalk": "", 
    "icon": "", 
    "idl": "", 
    "inform": "", 
    "informix-4gl": "", 
    "intercal": "", 
    "io": "", 
    "ioke": "", 
    "j": "", 
    "j#": "", 
    "jade": "", 
    "java": [
        "actframework", 
        "activiti", 
        "akka", 
        "android plot", 
        "apache accumulo", 
        "apache activemq", 
        "apache avalon", 
        "apache avro", 
        "apache axis", 
        "apache blur", 
        "apache bookkeeper", 
        "apache camel", 
        "apache cayenne", 
        "apache click", 
        "apache cocoon", 
        "apache commons", 
        "apache crunch", 
        "apache cxf", 
        "apache datafu", 
        "apache empire db", 
        "apache felix", 
        "apache flume", 
        "apache geronimo", 
        "apache giraph", 
        "apache hadoop", 
        "apache hbase", 
        "apache hive", 
        "apache jackrabbit", 
        "apache javanlp", 
        "apache jena", 
        "apache kafka", 
        "apache log4j", 
        "apache lucene", 
        "apache mahout", 
        "apache mesos", 
        "apache mina", 
        "apache nutch", 
        "apache oodt", 
        "apache oozie", 
        "apache opennlp", 
        "apache pdfbox", 
        "apache pig", 
        "apache pivot", 
        "apache poi", 
        "apache qpid", 
        "apache river", 
        "apache samza", 
        "apache shiroorg", 
        "apache sling", 
        "apache solr", 
        "apache sparkorg", 
        "apache storm", 
        "apache struts", 
        "apache tapestry", 
        "apache tika", 
        "apache tomcat", 
        "apache turbine", 
        "apache uima", 
        "apache usergrid", 
        "apache velocity", 
        "apache vxquery", 
        "apache wink", 
        "apache xerces", 
        "apache zookeeper", 
        "appfuse", 
        "axon", 
        "barracuda", 
        "beads", 
        "bigfaceless", 
        "biojava", 
        "birt", 
        "bluecove", 
        "bouncy castle ", 
        "cascading", 
        "checker", 
        "codename one", 
        "controlsfx", 
        "crawler4j", 
        "dagger", 
        "deeplearning4j", 
        "directwebremoting", 
        "drools", 
        "dropwizard jersey", 
        "easy rules", 
        "eclipselink", 
        "ehcache", 
        "ejml ", 
        "facebook4j", 
        "flexive", 
        "fmj", 
        "frame4j", 
        "freemarker", 
        "gcviewer", 
        "geoapi", 
        "geotools", 
        "glassfish", 
        "google gson", 
        "google guava", 
        "google guice", 
        "google web toolkit", 
        "gstreamer", 
        "gxt", 
        "hibernate", 
        "hk2", 
        "hsqldb", 
        "ibatis", 
        "infinispan", 
        "itext", 
        "jackcess", 
        "jackson", 
        "jasper reports", 
        "java media framework", 
        "javassist", 
        "javers", 
        "jaxp", 
        "jboss seam", 
        "jbpm", 
        "jcabi", 
        "jdom", 
        "jeddict", 
        "jello", 
        "jersey", 
        "jess", 
        "jetty", 
        "jfreechart", 
        "jidesoft", 
        "jlisa", 
        "jmock", 
        "jmonkeyengine", 
        "joda time", 
        "jogamp", 
        "jooby", 
        "jppf", 
        "jprofiler", 
        "jrockit", 
        "jruleengine", 
        "jsf", 
        "jsonlib", 
        "jsoup", 
        "jspx", 
        "jsyn", 
        "jts topology", 
        "junit", 
        "liquibase", 
        "logback", 
        "lombok", 
        "loopj", 
        "lwjgl", 
        "mapdb", 
        "mockito", 
        "mybatis", 
        "nd4j", 
        "netty", 
        "neuroph", 
        "ninja", 
        "opencsv", 
        "opencv", 
        "openrules", 
        "openxava", 
        "oracle", 
        "orientdb", 
        "ormlite", 
        "pi4j", 
        "play", 
        "primefaces", 
        "prova", 
        "quartz", 
        "quasar", 
        "rabbitmq", 
        "ratpack", 
        "reactor", 
        "resteasy", 
        "restfb", 
        "restlet", 
        "sax", 
        "scribejava", 
        "selenide", 
        "selenium", 
        "slf4j", 
        "slick2d", 
        "smack", 
        "sonarlint", 
        "sonarqube", 
        "spock", 
        "spring ", 
        "spring ", 
        "spring aop", 
        "spring batch", 
        "spring boot", 
        "spring core", 
        "spring data", 
        "spring data mongodb", 
        "spring data neo4j", 
        "spring hateoas", 
        "spring integration", 
        "spring ldap", 
        "spring mvc", 
        "spring roo", 
        "spring security", 
        "spring session", 
        "spring social", 
        "spring xd", 
        "stormpath", 
        "stringtemplate", 
        "suanshu", 
        "testng", 
        "thymeleaf", 
        "twitter4j", 
        "vaadin", 
        "vertx", 
        "vraptor", 
        "wildfly", 
        "wordcram", 
        "wso2 api manager", 
        "wso2 app manager", 
        "wso2 esb", 
        "wso2 governance registry", 
        "wso2 identity server", 
        "wso2 machine learner", 
        "wso2 message broker", 
        "xuggler", 
        "zkoss"
    ], 
    "java fx script": "", 
    "javascript": "", 
    "jscript": "", 
    "jscript.net": "", 
    "julia": "", 
    "korn shell": "", 
    "kotlin": "", 
    "labview": "", 
    "ladder logic": "", 
    "lasso": "", 
    "limbo": "", 
    "lingo": "", 
    "lisp": "", 
    "logo": "", 
    "logtalk": "", 
    "lotusscript": "", 
    "lpc": "", 
    "lua": "", 
    "lustre": "", 
    "m4": "", 
    "mad": "", 
    "magic": "", 
    "magik": "", 
    "malbolge": "", 
    "mantis": "", 
    "maple": "", 
    "mathematica": "", 
    "matlab": "", 
    "max/msp": "", 
    "maxscript": "", 
    "mel": "", 
    "mercury": "", 
    "mirah": "", 
    "miva": "", 
    "ml": "", 
    "modula-2": "", 
    "modula-3": "", 
    "monkey": "", 
    "moo": "", 
    "moto": "", 
    "ms-dos batch": "", 
    "mumps": "", 
    "natural": "", 
    "nemerle": "", 
    "nimrod": "", 
    "nqc": "", 
    "nsis": "", 
    "nu": "", 
    "nxt-g": "", 
    "oberon": "", 
    "object rexx": "", 
    "objective-c": "", 
    "objective-j": "", 
    "ocaml": "", 
    "occam": "", 
    "ooc": "", 
    "opa": "", 
    "opencl": "", 
    "openedge abl": "", 
    "opl": "", 
    "oz": "", 
    "paradox": "", 
    "parrot": "", 
    "pascal": "", 
    "perl": "", 
    "php": "", 
    "pike": "", 
    "pilot": "", 
    "i": "", 
    "sql": "", 
    "pliant": "", 
    "postscript": "", 
    "pov-ray": "", 
    "powerbasic": "", 
    "powerscript": "", 
    "powershell": "", 
    "processing": "", 
    "prolog": "", 
    "puppet": "", 
    "pure data": "", 
    "python": [
        "django", 
        "flask", 
        "turbogears", 
        "web2py", 
        "cubicweb", 
        "django-hotsauce", 
        "giotto", 
        "grok", 
        "pylons", 
        "reahl", 
        "wheezy.web", 
        "zope2", 
        "glashammer", 
        "karrigell", 
        "kiss.py", 
        "lino", 
        "nagare", 
        "porcupine", 
        "pylatte", 
        "spyce", 
        "tipfy", 
        "tornado", 
        "watson-framework", 
        "webapp2", 
        "webbot", 
        "webcore", 
        "web.py", 
        "webware for python", 
        "werkzeug", 
        "whiff", 
        "bottle", 
        "cherrypy", 
        "flask", 
        "hug", 
        "pyramid", 
        "pylons project", 
        "nevow", 
        "quixote"
    ], 
    "q": "", 
    "r": "", 
    "racket": "", 
    "realbasic": "", 
    "rebol": "", 
    "revolution": "", 
    "rexx": "", 
    "rpg": "", 
    "ruby": "", 
    "rust": "", 
    "s": "", 
    "s-plus": "", 
    "sas": "", 
    "sather": "", 
    "scala": "", 
    "scheme": "", 
    "scilab": "", 
    "scratch": "", 
    "sed": "", 
    "seed7": "", 
    "self": "", 
    "shell": "", 
    "signal": "", 
    "simula": "", 
    "simulink": "", 
    "slate": "", 
    "smalltalk": "", 
    "smarty": "", 
    "spark": "", 
    "spss": "", 
    "sqr": "", 
    "squeak": "", 
    "squirrel": "", 
    "standard ml": "", 
    "suneido": "", 
    "supercollider": "", 
    "tacl": "", 
    "tcl": "", 
    "tex": "", 
    "thinbasic": "", 
    "tom": "", 
    "transact-sql": "", 
    "turing": "", 
    "typescript": "", 
    "vala": "", 
    "vbscript": "", 
    "verilog": "", 
    "vhdl": "", 
    "viml": "", 
    "visual basic .net": "", 
    "webdna": "", 
    "whitespace": "", 
    "x10": "", 
    "xbase": "", 
    "xbase++": "", 
    "xen": "", 
    "xpl": "", 
    "xquery": "", 
    "xslt": "", 
    "yacc": "", 
    "yorick": "", 
    "z shell": ""
}